uipath_connectors/dropbox_dropbox/__init__.py
uipath_connectors/dropbox_dropbox/client.py
uipath_connectors/dropbox_dropbox/errors.py
uipath_connectors/dropbox_dropbox/py.typed
uipath_connectors/dropbox_dropbox/types.py
uipath_connectors/dropbox_dropbox/api/__init__.py
uipath_connectors/dropbox_dropbox/api/add_team_members/__init__.py
uipath_connectors/dropbox_dropbox/api/add_team_members/add_members.py
uipath_connectors/dropbox_dropbox/api/create_folder/__init__.py
uipath_connectors/dropbox_dropbox/api/create_folder/create_folders.py
uipath_connectors/dropbox_dropbox/api/create_shared_links/__init__.py
uipath_connectors/dropbox_dropbox/api/create_shared_links/create_shared_links.py
uipath_connectors/dropbox_dropbox/api/delete_file/__init__.py
uipath_connectors/dropbox_dropbox/api/delete_file/delete_file.py
uipath_connectors/dropbox_dropbox/api/delete_folder/__init__.py
uipath_connectors/dropbox_dropbox/api/delete_folder/delete_folders.py
uipath_connectors/dropbox_dropbox/api/files_copy/__init__.py
uipath_connectors/dropbox_dropbox/api/files_copy/copy_files.py
uipath_connectors/dropbox_dropbox/api/files_download/__init__.py
uipath_connectors/dropbox_dropbox/api/files_download/file_downloads.py
uipath_connectors/dropbox_dropbox/api/files_search/__init__.py
uipath_connectors/dropbox_dropbox/api/files_search/files_search.py
uipath_connectors/dropbox_dropbox/api/folders_copy/__init__.py
uipath_connectors/dropbox_dropbox/api/folders_copy/copy_folder.py
uipath_connectors/dropbox_dropbox/api/get_file_details/__init__.py
uipath_connectors/dropbox_dropbox/api/get_file_details/get_file_details.py
uipath_connectors/dropbox_dropbox/api/get_folder_contents/__init__.py
uipath_connectors/dropbox_dropbox/api/get_folder_contents/get_folder_content.py
uipath_connectors/dropbox_dropbox/api/get_shared_links/__init__.py
uipath_connectors/dropbox_dropbox/api/get_shared_links/get_shared_link.py
uipath_connectors/dropbox_dropbox/api/members/__init__.py
uipath_connectors_dropbox_dropbox-1.6.5.dev12.dist-info/METADATA
uipath_connectors_dropbox_dropbox-1.6.5.dev12.dist-info/WHEEL
uipath_connectors_dropbox_dropbox-1.6.5.dev12.dist-info/entry_points.txt
uipath_connectors_dropbox_dropbox-1.6.5.dev12.dist-info/top_level.txt
uipath_connectors_dropbox_dropbox-1.6.5.dev12.dist-info/RECORD
